neeraj_poetry_demo/__init__.py
neeraj_poetry_demo-0.1.0.dist-info/WHEEL
neeraj_poetry_demo-0.1.0.dist-info/METADATA
neeraj_poetry_demo-0.1.0.dist-info/RECORD
