Metadata-Version: 2.1
Name: neeraj-poetry-demo
Version: 0.1.0
Summary: 
Author: Neeraj Chaudhary
Author-email: neeraj_chaudhary@mcafee.com
Requires-Python: >=2.7,<3.0
Classifier: Programming Language :: Python :: 2
Classifier: Programming Language :: Python :: 2.7
Requires-Dist: pendulum (>=2.0,<3.0)
